tests/__init__.py
tests/test_algorithm.py
tests/test_api_shim.py
tests/test_assets.py
tests/test_bar_data.py
tests/test_benchmark.py
tests/test_clock.py
tests/test_continuous_futures.py
tests/test_data_portal.py
tests/test_examples.py
tests/test_exception_handling.py
tests/test_execution_styles.py
tests/test_fetcher.py
tests/test_finance.py
tests/test_history.py
tests/test_labelarray.py
tests/test_memoize.py
tests/test_panel_bar_reader.py
tests/test_restrictions.py
tests/test_security_list.py
tests/test_testing.py
tests/test_tradesimulation.py
tests/calendars/__init__.py
tests/calendars/test_calendar_dispatcher.py
tests/calendars/test_cfe_calendar.py
tests/calendars/test_cme_calendar.py
tests/calendars/test_ice_calendar.py
tests/calendars/test_nyse_calendar.py
tests/calendars/test_szsh_calendar.py
tests/calendars/test_trading_calendar.py
tests/data/__init__.py
tests/data/test_cn_equity_pricing.py
tests/data/test_dispatch_bar_reader.py
tests/data/test_minute_bars.py
tests/data/test_resample.py
tests/data/test_szsh.py
tests/data/test_us_equity_pricing.py
tests/data/bundles/__init__.py
tests/data/bundles/test_core.py
tests/data/bundles/test_csvdir.py
tests/data/bundles/test_quandl.py
tests/finance/__init__.py
tests/finance/test_blotter.py
tests/finance/test_cancel_policy.py
tests/finance/test_commissions.py
tests/finance/test_risk.py
tests/finance/test_slippage.py
tests/finance/test_transaction.py
tests/optimize/__init__.py
tests/optimize/test_constraints.py
tests/optimize/test_objectives.py
tests/optimize/test_opt_exception.py
tests/pipeline/__init__.py
tests/pipeline/base.py
tests/pipeline/test_adjusted_array.py
tests/pipeline/test_adjustment.py
tests/pipeline/test_alias.py
tests/pipeline/test_blaze.py
tests/pipeline/test_classifier.py
tests/pipeline/test_column.py
tests/pipeline/test_downsampling.py
tests/pipeline/test_dtypes.py
tests/pipeline/test_engine.py
tests/pipeline/test_events.py
tests/pipeline/test_factor.py
tests/pipeline/test_filter.py
czipline_pro-1.13.2.dist-info/AUTHORS
czipline_pro-1.13.2.dist-info/LICENSE
czipline_pro-1.13.2.dist-info/METADATA
czipline_pro-1.13.2.dist-info/WHEEL
czipline_pro-1.13.2.dist-info/top_level.txt
czipline_pro-1.13.2.dist-info/RECORD
